{
  "nombre": "0021.1.1.7. identificador — longitud 2 (409)",
  "expectedHttpStatus": 200,
  "expectedCodigoError": 409,
  "expectedTipo": "parametro",
  "algoritmoCifrado": "aes-256-cbc",
  "body": {
    "idCanal": "{{CANAL_EMISOR}}",
    "validador": "{{CANAL_VALIDADOR}}",
    "peticion": {
      "idPeticion": "{{SWIFT_CANAL_EMISOR}}{{$timestamp}}",
      "metodo": "0021",
      "solicitudes": [
        {
          "idSolicitud": "1",
          "parametros": {
            "identificador": "ab",
            "tipoIdentificador": "COMERCIO"
          }
        }
      ]
    }
  }
}
