{
  "nombre": "0019.1.1.5. identificador — tipo boolean (409)",
  "expectedHttpStatus": 200,
  "expectedCodigoError": 409,
  "expectedTipo": "parametro",
  "algoritmoCifrado": "aes-256-cbc",
  "body": {
    "idCanal": "{{CANAL_EMISOR}}",
    "validador": "{{CANAL_VALIDADOR}}",
    "peticion": {
      "idPeticion": "{{SWIFT_CANAL_EMISOR}}{{$timestamp}}",
      "metodo": "0019",
      "solicitudes": [
        {
          "idSolicitud": "1",
          "parametros": {
            "identificador": true,
            "tipoIdentificador": "CELULAR"
          }
        }
      ]
    }
  }
}
